{
    "projects" : [
        {
            "id": 0,
            "project_name": "Random Quote Generator",
            "description": "Generates random quotes from an array, either after a set time interval or via the user clicking an on-screen button.",
            "technologies": ["HTML", "CSS", "JavaScript"],
            "live_link": "https://dani-gonzo.github.io/techdegree-project1/",
            "github_link": "https://github.com/Dani-Gonzo/techdegree-project1",
            "landing_image": "project1Landing.jpg",
            "image_urls": ["project1Addtl.jpg", "project1Addtl2.jpg"]
        },
        {
            "id": 1,
            "project_name": "List Pagination and Filtering",
            "description": "Displays 10 student records per page, dynamically generating the number of page links needed for the size of the list. Search bar generates student records as the user types, also dynamically generating page links as the number of matching records changes.",
            "technologies": ["HTML", "CSS", "JavaScript"],
            "live_link": "https://dani-gonzo.github.io/techdegree-project2/",
            "github_link": "https://github.com/Dani-Gonzo/techdegree-project2",
            "landing_image": "project2Landing.jpg",
            "image_urls": ["project2Addtl.jpg", "project2Addtl2.jpg"]
        },
        {
            "id": 2,
            "project_name": "Interactive Form",
            "description":"Practice in making a \"smart form\" that reacts to user input while maintaining Progressive Enhancement.",
            "technologies": ["HTML", "CSS", "JavaScript", "JQuery"],
            "live_link": "https://dani-gonzo.github.io/techdegree-project3/",
            "github_link": "https://github.com/Dani-Gonzo/techdegree-project3",
            "landing_image": "project3Landing.jpg",
            "image_urls": ["project3Addtl.jpg", "project3Addtl2.jpg", "project3Addtl3.jpg"]
        },
        {
            "id": 3,
            "project_name": "OOP Game Show App",
            "description": "Practice using object-oriented JavaScript to make an interactive hangman game through the browser.",
            "technologies": ["HTML", "CSS", "JavaScript", "JQuery"],
            "live_link": "https://dani-gonzo.github.io/techdegree-project4/",
            "github_link": "https://github.com/Dani-Gonzo/techdegree-project4",
            "landing_image": "project4Landing.jpg",
            "image_urls": ["project4Addtl.jpg", "project4Addtl2.jpg", "project4Addtl3.jpg"]
        },
        {
            "id": 4,
            "project_name": "Public API Requests",
            "description": "Practice using fetch requests to build an employee directory.",
            "technologies": ["HTML", "CSS", "JavaScript", "JQuery", "Random User API"],
            "live_link": "https://dani-gonzo.github.io/techdegree-project5/",
            "github_link": "https://github.com/Dani-Gonzo/techdegree-project5",
            "landing_image": "project5Landing.jpg",
            "image_urls": ["project5Addtl.jpg", "project5Addtl2.jpg", "project5Addtl3.jpg"]
        },
        {
            "id": 5,
            "project_name": "Four In A Row Game",
            "description": "Draws up a four-in-a-row gameboard in the browser and allows the user to move and drop the game pieces. Switches between player 1 and player 2 via changing the game piece color.",
            "technologies": ["HTML", "CSS", "JavaScript", "JQuery"],
            "live_link": "https://dani-gonzo.github.io/four-in-a-row/",
            "github_link": "https://github.com/Dani-Gonzo/four-in-a-row",
            "landing_image": "projectGameLanding.jpg",
            "image_urls": ["projectGameAddtl.jpg", "projectGameAddtl2.jpg"]
        }
    ]
}